MANIFEST.in
README.md
setup.py
add_service/__init__.py
add_service/__main__.py
add_service/main.py
add_service.egg-info/PKG-INFO
add_service.egg-info/SOURCES.txt
add_service.egg-info/dependency_links.txt
add_service.egg-info/entry_points.txt
add_service.egg-info/top_level.txt