Metadata-Version: 2.1
Name: add-service
Version: 1.0.0
Summary: CLI tool for simply adding startup item by systemd.
Home-page: https://github.com/DIYer22/add_service
Author: DIYer22
Author-email: ylxx@live.com
License: UNKNOWN
Platform: UNKNOWN
Classifier: Topic :: Software Development :: Libraries :: Python Modules
Classifier: License :: OSI Approved :: MIT License
Classifier: Operating System :: OS Independent
